[{"mainprice":[{"src":"../img/m1.jpg",
  "title":"加拿大原装进口 Orijen渴望狗粮 无谷类幼犬配方狗粮 2kg",
  "price1":"￥255.00",
  "price2":"15.00"},
  {"src":"../img/m2.jpg",
  "title":"加拿大原装进口 Orijen渴望狗粮 六种鱼肉+美毛专用配方全犬粮 2kg",
  "price1":"￥290.00",
  "price2":"19.80"},
  {"src":"../img/m3.jpg",
  "title":"海洋之星 三文鱼成犬粮 小颗粒 1.5kg",
  "price1":"￥140.00",
  "price2":"20.80"},
  {"src":"../img/m4.jpg",
  "title":"澳大利亚贵族Natures Gift 鸸鹋油羊肉米饭 成犬粮 15kg",
  "price1":"￥385.00",
  "price2":"12.80"}
  ,
  {"src":"../img/m13.jpg",
  "title":"拿大原装进口 爱肯拿Acana 小型犬幼犬母犬配方粮(鸡肉+鱼) 2kg",
  "price1":"￥190.00",
  "price2":"12.80"}
  ,
  {"src":"../img/m6.jpg",
  "title":"【保质期至2018-01-08】加拿大原装进口 爱肯拿Acana 无谷深海鱼配",
  "price1":"￥885.00",
  "price2":"12.80"}
  ,
  {"src":"../img/m7.jpg",
  "title":"比利时原装进口 欧帝亿IMPERIAL PAW 小型犬幼犬鸡肉配方粮 1.5kg",
  "price1":"￥163.00",
  "price2":"12.80"}
  ,
  {"src":"../img/m8.jpg",
  "title":"澳洲原装进口 澳维加OZVIC 全犬种成犬羊肉米饭配方粮 10kg",
  "price1":"￥338.00",
  "price2":"12.80"}
  
  
  
  ]},
  {"mainprice":[{"src":"../img/m1.jpg",
  "title":"加拿大原装进口 Orijen渴望狗粮 无谷类幼犬配方狗粮 2kg",
  "price1":"￥425.00",
  "price2":"15.00"},
  {"src":"../img/m2.jpg",
  "title":"加拿大原装进口 Orijen渴望狗粮 六种鱼肉+美毛专用配方全犬粮 2kg",
  "price1":"￥290.00",
  "price2":"19.80"},
  {"src":"../img/m9.jpg",
  "title":"海洋之星 三文鱼成犬粮 小颗粒 1.5kg",
  "price1":"￥320.00",
  "price2":"20.80"},
  {"src":"../img/m4.jpg",
  "title":"澳大利亚贵族Natures Gift 鸸鹋油羊肉米饭 成犬粮 15kg",
  "price1":"￥385.00",
  "price2":"12.80"}
  ,
  {"src":"../img/m13.jpg",
  "title":"拿大原装进口 爱肯拿Acana 小型犬幼犬母犬配方粮(鸡肉+鱼) 2kg",
  "price1":"￥190.00",
  "price2":"12.80"}
  ,
  {"src":"../img/m6.jpg",
  "title":"【保质期至2018-01-08】加拿大原装进口 爱肯拿Acana 无谷深海鱼配",
  "price1":"￥885.00",
  "price2":"12.80"}
  ,
  {"src":"../img/m7.jpg",
  "title":"比利时原装进口 欧帝亿IMPERIAL PAW 小型犬幼犬鸡肉配方粮 1.5kg",
  "price1":"￥123.00",
  "price2":"12.80"}
  ,
  {"src":"../img/m8.jpg",
  "title":"澳洲原装进口 澳维加OZVIC 全犬种成犬羊肉米饭配方粮 10kg",
  "price1":"￥338.00",
  "price2":"12.80"}
  ]},
  
  
  {"mainprice":[{"src":"../img/m13.jpg",
  "title":"加拿大原装进口 Orijen渴望狗粮 无谷类幼犬配方狗粮 2kg",
  "price1":"￥962.00",
  "price2":"15.00"},
  {"src":"../img/m12.jpg",
  "title":"加拿大原装进口 Orijen渴望狗粮 六种鱼肉+美毛专用配方全犬粮 2kg",
  "price1":"￥290.00",
  "price2":"19.80"},
  {"src":"../img/m4.jpg",
  "title":"澳大利亚贵族Natures Gift 鸸鹋油羊肉米饭 成犬粮 15kg",
  "price1":"￥385.00",
  "price2":"12.80"}
  ,
  {"src":"../img/m3.jpg",
  "title":"海洋之星 三文鱼成犬粮 小颗粒 1.5kg",
  "price1":"￥746.00",
  "price2":"20.80"},
  
  {"src":"../img/m15.jpg",
  "title":"拿大原装进口 爱肯拿Acana 小型犬幼犬母犬配方粮(鸡肉+鱼) 2kg",
  "price1":"￥190.00",
  "price2":"12.80"},
  {"src":"../img/m7.jpg",
  "title":"比利时原装进口 欧帝亿IMPERIAL PAW 小型犬幼犬鸡肉配方粮 1.5kg",
  "price1":"￥163.00",
  "price2":"12.80"}
  ,
  {"src":"../img/m16.jpg",
  "title":"【保质期至2018-01-08】加拿大原装进口 爱肯拿Acana 无谷深海鱼配",
  "price1":"￥249.00",
  "price2":"12.80"}
  
  ,
  {"src":"../img/m8.jpg",
  "title":"澳洲原装进口 澳维加OZVIC 全犬种成犬羊肉米饭配方粮 10kg",
  "price1":"￥338.00",
  "price2":"12.80"}
  
  
  
  ]},
  {"mainprice":[{"src":"../img/m7.jpg",
  "title":"加拿大原装进口 Orijen渴望狗粮 无谷类幼犬配方狗粮 2kg",
  "price1":"￥615.00",
  "price2":"15.00"},
  {"src":"../img/m10.jpg",
  "title":"加拿大原装进口 Orijen渴望狗粮 六种鱼肉+美毛专用配方全犬粮 2kg",
  "price1":"￥290.00",
  "price2":"19.80"},
  {"src":"../img/m3.jpg",
  "title":"海洋之星 三文鱼成犬粮 小颗粒 1.5kg",
  "price1":"￥140.00",
  "price2":"20.80"},
  {"src":"../img/m9.jpg",
  "title":"拿大原装进口 爱肯拿Acana 小型犬幼犬母犬配方粮(鸡肉+鱼) 2kg",
  "price1":"￥190.00",
  "price2":"12.80"},
  {"src":"../img/m14.jpg",
  "title":"澳大利亚贵族Natures Gift 鸸鹋油羊肉米饭 成犬粮 15kg",
  "price1":"￥385.00",
  "price2":"12.80"}
  
  ,
  {"src":"../img/m6.jpg",
  "title":"【保质期至2018-01-08】加拿大原装进口 爱肯拿Acana 无谷深海鱼配",
  "price1":"￥885.00",
  "price2":"12.80"},
  {"src":"../img/m8.jpg",
  "title":"澳洲原装进口 澳维加OZVIC 全犬种成犬羊肉米饭配方粮 10kg",
  "price1":"￥338.00",
  "price2":"12.80"}
  ,
  {"src":"../img/m7.jpg",
  "title":"比利时原装进口 欧帝亿IMPERIAL PAW 小型犬幼犬鸡肉配方粮 1.5kg",
  "price1":"￥163.00",
  "price2":"12.80"}
  
  ]},
  
  
  
  {"mainprice":[{"src":"../img/m1.jpg",
  "title":"加拿大原装进口 Orijen渴望狗粮 无谷类幼犬配方狗粮 2kg",
  "price1":"￥255.00",
  "price2":"15.00"},
  {"src":"../img/m2.jpg",
  "title":"加拿大原装进口 Orijen渴望狗粮 六种鱼肉+美毛专用配方全犬粮 2kg",
  "price1":"￥290.00",
  "price2":"19.80"},
  {"src":"../img/m4.jpg",
  "title":"澳大利亚贵族Natures Gift 鸸鹋油羊肉米饭 成犬粮 15kg",
  "price1":"￥385.00",
  "price2":"12.80"}
  ,
  {"src":"../img/m5.jpg",
  "title":"拿大原装进口 爱肯拿Acana 小型犬幼犬母犬配方粮(鸡肉+鱼) 2kg",
  "price1":"￥190.00",
  "price2":"12.80"},
  {"src":"../img/m3.jpg",
  "title":"海洋之星 三文鱼成犬粮 小颗粒 1.5kg",
  "price1":"￥140.00",
  "price2":"20.80"},
  
  {"src":"../img/m6.jpg",
  "title":"【保质期至2018-01-08】加拿大原装进口 爱肯拿Acana 无谷深海鱼配",
  "price1":"￥885.00",
  "price2":"12.80"},
  {"src":"../img/m8.jpg",
  "title":"澳洲原装进口 澳维加OZVIC 全犬种成犬羊肉米饭配方粮 10kg",
  "price1":"￥338.00",
  "price2":"12.80"}
  ,
  {"src":"../img/m7.jpg",
  "title":"比利时原装进口 欧帝亿IMPERIAL PAW 小型犬幼犬鸡肉配方粮 1.5kg",
  "price1":"￥163.00",
  "price2":"12.80"}
  
  
  
  
  ]},
  {"mainprice":[{"src":"../img/m1.jpg",
  "title":"加拿大原装进口 Orijen渴望狗粮 无谷类幼犬配方狗粮 2kg",
  "price1":"￥255.00",
  "price2":"15.00"},
  {"src":"../img/m2.jpg",
  "title":"加拿大原装进口 Orijen渴望狗粮 六种鱼肉+美毛专用配方全犬粮 2kg",
  "price1":"￥290.00",
  "price2":"19.80"},
  {"src":"../img/m3.jpg",
  "title":"海洋之星 三文鱼成犬粮 小颗粒 1.5kg",
  "price1":"￥140.00",
  "price2":"20.80"},
  {"src":"../img/m4.jpg",
  "title":"澳大利亚贵族Natures Gift 鸸鹋油羊肉米饭 成犬粮 15kg",
  "price1":"￥385.00",
  "price2":"12.80"}
  ,
  {"src":"../img/m5.jpg",
  "title":"拿大原装进口 爱肯拿Acana 小型犬幼犬母犬配方粮(鸡肉+鱼) 2kg",
  "price1":"￥190.00",
  "price2":"12.80"}
  ,
  {"src":"../img/m6.jpg",
  "title":"【保质期至2018-01-08】加拿大原装进口 爱肯拿Acana 无谷深海鱼配",
  "price1":"￥885.00",
  "price2":"12.80"}
  ,
  {"src":"../img/m7.jpg",
  "title":"比利时原装进口 欧帝亿IMPERIAL PAW 小型犬幼犬鸡肉配方粮 1.5kg",
  "price1":"￥163.00",
  "price2":"12.80"}
  ,
  {"src":"../img/m8.jpg",
  "title":"澳洲原装进口 澳维加OZVIC 全犬种成犬羊肉米饭配方粮 10kg",
  "price1":"￥338.00",
  "price2":"12.80"}
  ]},
  
  
  
  {"mainprice":[{"src":"../img/m1.jpg",
  "title":"加拿大原装进口 Orijen渴望狗粮 无谷类幼犬配方狗粮 2kg",
  "price1":"￥255.00",
  "price2":"15.00"},
  {"src":"../img/m2.jpg",
  "title":"加拿大原装进口 Orijen渴望狗粮 六种鱼肉+美毛专用配方全犬粮 2kg",
  "price1":"￥290.00",
  "price2":"19.80"},
  {"src":"../img/m3.jpg",
  "title":"海洋之星 三文鱼成犬粮 小颗粒 1.5kg",
  "price1":"￥140.00",
  "price2":"20.80"},
  {"src":"../img/m4.jpg",
  "title":"澳大利亚贵族Natures Gift 鸸鹋油羊肉米饭 成犬粮 15kg",
  "price1":"￥385.00",
  "price2":"12.80"}
  ,
  {"src":"../img/m5.jpg",
  "title":"拿大原装进口 爱肯拿Acana 小型犬幼犬母犬配方粮(鸡肉+鱼) 2kg",
  "price1":"￥190.00",
  "price2":"12.80"}
  ,
  {"src":"../img/m6.jpg",
  "title":"【保质期至2018-01-08】加拿大原装进口 爱肯拿Acana 无谷深海鱼配",
  "price1":"￥885.00",
  "price2":"12.80"}
  ,
  {"src":"../img/m7.jpg",
  "title":"比利时原装进口 欧帝亿IMPERIAL PAW 小型犬幼犬鸡肉配方粮 1.5kg",
  "price1":"￥163.00",
  "price2":"12.80"}
  ,
  {"src":"../img/m8.jpg",
  "title":"澳洲原装进口 澳维加OZVIC 全犬种成犬羊肉米饭配方粮 10kg",
  "price1":"￥338.00",
  "price2":"12.80"}
  
  
  
  ]},
  {"mainprice":[{"src":"../img/m1.jpg",
  "title":"加拿大原装进口 Orijen渴望狗粮 无谷类幼犬配方狗粮 2kg",
  "price1":"￥255.00",
  "price2":"15.00"},
  {"src":"../img/m2.jpg",
  "title":"加拿大原装进口 Orijen渴望狗粮 六种鱼肉+美毛专用配方全犬粮 2kg",
  "price1":"￥290.00",
  "price2":"19.80"},
  {"src":"../img/m3.jpg",
  "title":"海洋之星 三文鱼成犬粮 小颗粒 1.5kg",
  "price1":"￥140.00",
  "price2":"20.80"},
  {"src":"../img/m4.jpg",
  "title":"澳大利亚贵族Natures Gift 鸸鹋油羊肉米饭 成犬粮 15kg",
  "price1":"￥385.00",
  "price2":"12.80"}
  ,
  {"src":"../img/m5.jpg",
  "title":"拿大原装进口 爱肯拿Acana 小型犬幼犬母犬配方粮(鸡肉+鱼) 2kg",
  "price1":"￥190.00",
  "price2":"12.80"}
  ,
  {"src":"../img/m6.jpg",
  "title":"【保质期至2018-01-08】加拿大原装进口 爱肯拿Acana 无谷深海鱼配",
  "price1":"￥885.00",
  "price2":"12.80"}
  ,
  {"src":"../img/m7.jpg",
  "title":"比利时原装进口 欧帝亿IMPERIAL PAW 小型犬幼犬鸡肉配方粮 1.5kg",
  "price1":"￥163.00",
  "price2":"12.80"}
  ,
  {"src":"../img/m8.jpg",
  "title":"澳洲原装进口 澳维加OZVIC 全犬种成犬羊肉米饭配方粮 10kg",
  "price1":"￥338.00",
  "price2":"12.80"}
  ]}
  
  
  
  
  

]